klein_config/__init__.py
klein_config/config.py
klein_config-4.0.2.dist-info/LICENSE.txt
klein_config-4.0.2.dist-info/METADATA
klein_config-4.0.2.dist-info/WHEEL
klein_config-4.0.2.dist-info/top_level.txt
klein_config-4.0.2.dist-info/zip-safe
klein_config-4.0.2.dist-info/RECORD
