Metadata-Version: 2.1
Name: klein-config
Version: 4.0.2
Summary: Read and manage config from environment variables and files
Home-page: https://github.com/mdcatapult/py-config
Author: Matthew Cockayne, Mark Laing, Gemma Holliday, Roman Ma
License: Apache V2
License-File: LICENSE.txt
Requires-Dist: pyhocon
Requires-Dist: pyyaml <7,>=6
